treemind/__init__.py
treemind/plot/_interaction_scatter_plot.py
treemind/plot/__init__.py
treemind/plot/_interaction_plot.py
treemind/plot/_importance_plot.py
treemind/plot/plot_utils.py
treemind/plot/_feature_plot.py
treemind/algorithm/explainer.pyi
treemind/algorithm/xgb.cpp
treemind/algorithm/explainer.cpython-310-darwin.so
treemind/algorithm/utils.cpp
treemind/algorithm/cb.cpp
treemind/algorithm/rule.cpython-310-darwin.so
treemind/algorithm/perp.cpp
treemind/algorithm/sk.cpp
treemind/algorithm/explainer.cpp
treemind/algorithm/__init__.py
treemind/algorithm/sk.cpython-310-darwin.so
treemind/algorithm/cb.cpython-310-darwin.so
treemind/algorithm/xgb.cpython-310-darwin.so
treemind/algorithm/lgb.cpp
treemind/algorithm/perp.cpython-310-darwin.so
treemind/algorithm/utils.cpython-310-darwin.so
treemind/algorithm/rule.cpp
treemind/algorithm/lgb.cpython-310-darwin.so
treemind-0.2.0.dist-info/RECORD
treemind-0.2.0.dist-info/WHEEL
treemind-0.2.0.dist-info/top_level.txt
treemind-0.2.0.dist-info/METADATA
treemind-0.2.0.dist-info/licenses/LICENSE
