Metadata-Version: 2.4
Name: treemind
Version: 0.2.0
Summary: feature and feature interaction analyzer for gradient boosting
Author-email: Samet Copur <sametcopur@yahoo.com>
License: BSD 3-Clause License
Project-URL: Documentation, https://treemind.readthedocs.io/en/latest/
Project-URL: Repository, https://github.com/sametcopur/treemind
Project-URL: Tracker, https://github.com/sametcopur/treemind/issues
Keywords: python,data-science,machine-learning,machine-learning-library,explainable-ai,gradient boosting
Classifier: Programming Language :: Python :: 3
Classifier: License :: OSI Approved :: BSD License
Classifier: Operating System :: OS Independent
Requires-Python: >=3.9
License-File: LICENSE
Requires-Dist: numpy>=1.24.4
Requires-Dist: pandas>=1.5.0
Requires-Dist: matplotlib>=3.7.0
Requires-Dist: seaborn>=0.12.0
Requires-Dist: tqdm
Dynamic: license-file
